llama_index/llms/openrouter/__init__.py
llama_index/llms/openrouter/base.py
llama_index/llms/openrouter/py.typed
llama_index_llms_openrouter-0.4.4.dist-info/METADATA
llama_index_llms_openrouter-0.4.4.dist-info/WHEEL
llama_index_llms_openrouter-0.4.4.dist-info/licenses/LICENSE
llama_index_llms_openrouter-0.4.4.dist-info/RECORD
