Metadata-Version: 2.4
Name: llama-index-llms-openrouter
Version: 0.4.4
Summary: llama-index llms openrouter integration
Author-email: Your Name <you@example.com>
License-Expression: MIT
License-File: LICENSE
Requires-Python: <4.0,>=3.9
Requires-Dist: llama-index-core<0.15,>=0.13.0
Requires-Dist: llama-index-llms-openai-like<0.7,>=0.5.0
